odoo/addons/mail_partner_opt_out/README.rst
odoo/addons/mail_partner_opt_out/__init__.py
odoo/addons/mail_partner_opt_out/__manifest__.py
odoo/addons/mail_partner_opt_out/i18n/mail_partner_opt_out.pot
odoo/addons/mail_partner_opt_out/models/__init__.py
odoo/addons/mail_partner_opt_out/models/res_partner.py
odoo/addons/mail_partner_opt_out/readme/CONTRIBUTORS.rst
odoo/addons/mail_partner_opt_out/readme/DESCRIPTION.rst
odoo/addons/mail_partner_opt_out/readme/USAGE.rst
odoo/addons/mail_partner_opt_out/static/description/icon.png
odoo/addons/mail_partner_opt_out/static/description/index.html
odoo/addons/mail_partner_opt_out/views/res_partner_views.xml
odoo13_addon_mail_partner_opt_out-13.0.1.0.1.dev4.dist-info/METADATA
odoo13_addon_mail_partner_opt_out-13.0.1.0.1.dev4.dist-info/WHEEL
odoo13_addon_mail_partner_opt_out-13.0.1.0.1.dev4.dist-info/top_level.txt
odoo13_addon_mail_partner_opt_out-13.0.1.0.1.dev4.dist-info/RECORD
